click_hotoffthehamster_alias/__init__.py
click_hotoffthehamster_alias-1.0.7.dist-info/LICENSE
click_hotoffthehamster_alias-1.0.7.dist-info/METADATA
click_hotoffthehamster_alias-1.0.7.dist-info/WHEEL
click_hotoffthehamster_alias-1.0.7.dist-info/RECORD
